voxcribe/__init__.py
voxcribe/voxcribe.py
voxcribe-1.0.0.dist-info/LICENSE
voxcribe-1.0.0.dist-info/METADATA
voxcribe-1.0.0.dist-info/WHEEL
voxcribe-1.0.0.dist-info/top_level.txt
voxcribe-1.0.0.dist-info/RECORD
