Metadata-Version: 2.1
Name: voxcribe
Version: 1.0.0
Summary: A lightweight audio transcription tool using speech recognition.
Home-page: https://github.com/VedantBarhate/voxcribe
Author: Vedant Barhate
Author-email: vedant.barhate27@example.com
License: MIT
Classifier: Programming Language :: Python :: 3
Classifier: License :: OSI Approved :: MIT License
Classifier: Operating System :: OS Independent
Requires-Python: >=3.6
License-File: LICENSE
Requires-Dist: speechrecognition
Requires-Dist: pydub
Requires-Dist: tqdm
